panda_pie/__init__.py
panda_pie/data_basics.py
panda_pie/data_generations.py
panda_pie/feature_engineering.py
panda_pie-0.1.1.dist-info/METADATA
panda_pie-0.1.1.dist-info/WHEEL
panda_pie-0.1.1.dist-info/top_level.txt
panda_pie-0.1.1.dist-info/RECORD
